mytools/__init__.py
mytools/button.py
mytools/chatbot.py
mytools/database.py
mytools/encrypt.py
mytools/getuser.py
mytools/logger.py
mytools/misc.py
mytools/text.py
mytools/trans.py
mytoolsID-1.1.1.1.dist-info/METADATA
mytoolsID-1.1.1.1.dist-info/WHEEL
mytoolsID-1.1.1.1.dist-info/top_level.txt
mytoolsID-1.1.1.1.dist-info/RECORD
