Metadata-Version: 2.1
Name: mytoolsID
Version: 1.1.1.1
Summary: Library of @NorSodikin
Home-page: https://t.me/NorSodikin
Author: NorSodikin
Author-email: admin@NorSodikin.com
License: MIT
Classifier: Programming Language :: Python :: 3
Classifier: Programming Language :: Python :: 3.8
Classifier: Programming Language :: Python :: 3.9
Classifier: Programming Language :: Python :: 3.10
Classifier: Programming Language :: Python :: 3.11
Classifier: Programming Language :: Python :: 3.12
Classifier: License :: OSI Approved :: MIT License
Classifier: Operating System :: OS Independent
Requires-Python: >=3.8, <3.13
Requires-Dist: cryptography
Requires-Dist: pyrogram-dev
Requires-Dist: tgcrypto
Requires-Dist: gpytranslate
Requires-Dist: google-generativeai
Requires-Dist: gtts
Requires-Dist: aiofiles
Requires-Dist: aiohttp
Requires-Dist: pyromod
